[
  {
    "ContainingType": "CRUD_WEB_API.Controllers.CrudController",
    "Method": "StudentDataEntry",
    "RelativePath": "api/Crud/StudentDataEntry",
    "HttpMethod": "POST",
    "IsController": true,
    "Order": 0,
    "Parameters": [
      {
        "Name": "Id",
        "Type": "System.Int32",
        "IsRequired": false
      },
      {
        "Name": "Name",
        "Type": "System.String",
        "IsRequired": false
      },
      {
        "Name": "Age",
        "Type": "System.Int32",
        "IsRequired": false
      }
    ],
    "ReturnTypes": []
  }
]